{
  "titulo": "Documentação de Testes e Validação do Sistema",
  "tipo": "tecnico",
  "contexto": "Adição de documentação detalhada sobre testes unitários, testes de integração, validação de performance e checklists de validação para o sistema de upload de documentos.",
  "status": "aberto",
  "data_inicio": "2024-01-18T00:00:00",
  "metadata": {
    "area": "qualidade",
    "prioridade": "alta",
    "impacto": "alto",
    "embates_relacionados": [
      "embate_upload_documentos.json",
      "embate_correcoes_upload.json",
      "embate_documentacao_adicional.json"
    ]
  },
  "argumentos": [
    {
      "autor": "Sistema",
      "tipo": "tecnico",
      "conteudo": "Testes Implementados:\n\n1. Testes Unitários:\n   - Mock do Supabase\n   - Testes de upload\n   - Validação de retornos\n   - Cobertura de código\n\n2. Testes de Integração:\n   - Pipeline completo\n   - Cenários de erro\n   - Validação end-to-end\n   - Consistência de dados",
      "data": "2024-01-18T00:00:00"
    },
    {
      "autor": "Sistema",
      "tipo": "tecnico",
      "conteudo": "Validação de Performance:\n\n1. Métricas Chave:\n   - Tempo de resposta\n   - Uso de recursos\n   - Throughput\n   - Latência\n\n2. Testes de Carga:\n   - Upload em massa\n   - Concorrência\n   - Limites do sistema\n   - Recuperação",
      "data": "2024-01-18T00:00:00"
    },
    {
      "autor": "Sistema",
      "tipo": "tecnico",
      "conteudo": "Processos de Validação:\n\n1. Checklist Pré-Produção:\n   - Verificações necessárias\n   - Configurações\n   - Permissões\n   - Backups\n\n2. Monitoramento:\n   - Alertas\n   - Dashboards\n   - Rate limits\n   - Integridade\n\n3. Manutenção:\n   - Rotação de logs\n   - Backup automático\n   - Verificações periódicas\n   - Atualizações",
      "data": "2024-01-18T00:00:00"
    }
  ]
}
